datafusion-stubs/__init__.pyi
datafusion-stubs/common.pyi
datafusion-stubs/expr.pyi
datafusion-stubs/functions.pyi
datafusion-stubs/object_store.pyi
datafusion-stubs/py.typed
datafusion-stubs/substrait.pyi
datafusion-stubs/_internal/__init__.pyi
datafusion-stubs/_internal/catalog.pyi
datafusion-stubs/_internal/config.pyi
datafusion-stubs/_internal/context.pyi
datafusion-stubs/_internal/dataframe.pyi
datafusion-stubs/_internal/functions.pyi
datafusion-stubs/_internal/physical_plan.pyi
datafusion-stubs/_internal/record_batch.pyi
datafusion-stubs/_internal/store.pyi
datafusion-stubs/_internal/substrait.pyi
datafusion-stubs/_internal/udaf.pyi
datafusion-stubs/_internal/udf.pyi
datafusion-stubs/_internal/common/__init__.pyi
datafusion-stubs/_internal/common/data_type.pyi
datafusion-stubs/_internal/common/df_field.pyi
datafusion-stubs/_internal/common/df_schema.pyi
datafusion-stubs/_internal/common/function.pyi
datafusion-stubs/_internal/common/schema.pyi
datafusion-stubs/_internal/expr/__init__.pyi
datafusion-stubs/_internal/expr/aggregate.pyi
datafusion-stubs/_internal/expr/aggregate_expr.pyi
datafusion-stubs/_internal/expr/alias.pyi
datafusion-stubs/_internal/expr/analyze.pyi
datafusion-stubs/_internal/expr/between.pyi
datafusion-stubs/_internal/expr/binary_expr.pyi
datafusion-stubs/_internal/expr/bool_expr.pyi
datafusion-stubs/_internal/expr/case.pyi
datafusion-stubs/_internal/expr/cast.pyi
datafusion-stubs/_internal/expr/column.pyi
datafusion-stubs/_internal/expr/conditional_expr.pyi
datafusion-stubs/_internal/expr/create_memory_table.pyi
datafusion-stubs/_internal/expr/create_view.pyi
datafusion-stubs/_internal/expr/cross_join.pyi
datafusion-stubs/_internal/expr/distinct.pyi
datafusion-stubs/_internal/expr/drop_table.pyi
datafusion-stubs/_internal/expr/empty_relation.pyi
datafusion-stubs/_internal/expr/exists.pyi
datafusion-stubs/_internal/expr/explain.pyi
datafusion-stubs/_internal/expr/extension.pyi
datafusion-stubs/_internal/expr/filter.pyi
datafusion_stubs-0.0.4.dist-info/LICENSE
datafusion_stubs-0.0.4.dist-info/METADATA
datafusion_stubs-0.0.4.dist-info/WHEEL
datafusion_stubs-0.0.4.dist-info/top_level.txt
datafusion_stubs-0.0.4.dist-info/RECORD
