Metadata-Version: 2.1
Name: datafusion-stubs
Version: 0.0.4
Summary: PEP 561 type stubs for Apache DataFusion Python Bindings
Home-page: https://github.com/3ok/datafusion-stubs
Author: Reda Bouaida
Author-email: reda.bouaida@outlook.com
License: Apache-2.0
Classifier: License :: OSI Approved :: Apache Software License
License-File: LICENSE
